{
  "mode": "full",
  "paywalled": false,
  "access": "open",
  "url": "https://marginalrevolution.com/marginalrevolution/2026/07/missing-women-on-indian-streets.html",
  "source": "Marginal Revolution",
  "title": "Missing women on Indian streets",
  "subtitle": null,
  "byline": "Tyler Cowen",
  "publishedAt": "2026-07-08T07:01:16.000Z",
  "contentHtml": "<blockquote><p>How absent are women from city streets in the developing world? We answer this question using GPS-linked wearable cameras and randomized street audits across ~900 kilometers of roads in greater Mumbai. Across 4000+ street images containing 23,000+ visible person observations, women account for 16.4% of visible people in Mumbai and 14.7% in Navi Mumbai, far below their population shares. We estimate pedestrian sex ratios of 239 and 223 women per 1,000 men, implying 71% and 76% of women expected based on residential ratios are missing from the streets. This pattern holds across road types, and private mobility does not explain the gap; women’s share on two-wheelers is lower still (8.4% and 5.7%). These results provide the first large-scale measurement of gender disparities&nbsp;in urban public life that self-reported data cannot capture.</p></blockquote>\n<p>That is from <a href=\"https://drive.google.com/file/d/1wpW9CKOgvRW7SD-xVc0ScycfUmRb9820/view\" target=\"_blank\" rel=\"noopener noreferrer\">a recent paper</a> by Varun Karekurve-Ramachandra and Gaurav Sood, via the excellent <a href=\"https://substack.com/@draliceevans\" target=\"_blank\" rel=\"noopener noreferrer\">Alice Evans</a>.&nbsp; Here is <a href=\"https://x.com/paulnovosad/status/2073134052681679306\" target=\"_blank\" rel=\"noopener noreferrer\">a related paper</a>, “The median married women in India leaves home for 30 minutes per day. On a typical day, 45% of married women don’t leave home at all.”</p>",
  "wordCount": 179,
  "imageCount": 0,
  "linkCount": 3
}
