{
  "mode": "full",
  "paywalled": false,
  "access": "open",
  "url": "https://marginalrevolution.com/marginalrevolution/2026/04/the-wisdom-of-roon.html",
  "source": "Marginal Revolution",
  "title": "The wisdom of Roon",
  "subtitle": null,
  "byline": "Tyler Cowen",
  "publishedAt": "2026-04-11T19:09:53.000Z",
  "contentHtml": "<blockquote><p>renaissance rationalization is a process that commodified itself rapidly: despite the europeans discovering most technology during the early modern period it spread everywhere within a few centuries, and the rate of spread has been increasing dramatically</p>\n<p>knowledge of the scientific frontier dissipates around the world faster as science has enabled better communication technologies.&nbsp;it’s getting even faster with INTELLIGENCE technologies which actually explain themselves and help you build them</p>\n<p>as we approach more powerful intelligence, the ability to train powerful models is self commodifying rather than building a huge and runaway advantage for a handful of recursive self improvers. this is one reason why you should expect almost all of the benefits of superintelligence to be captured by the public</p></blockquote>\n<p>Here is <a href=\"https://x.com/tszzl/status/2042077326452896244\" target=\"_blank\" rel=\"noopener noreferrer\">the tweet</a>.&nbsp; That said, it would be useful to relax constraints on the supply of both energy and land, so that the benefits could diffuse more widely yet.</p>",
  "wordCount": 150,
  "imageCount": 0,
  "linkCount": 1
}
