{
  "mode": "full",
  "paywalled": false,
  "access": "open",
  "url": "https://marginalrevolution.com/marginalrevolution/2026/05/conscious-introspection-leads-to-more-self-deception.html",
  "source": "Marginal Revolution",
  "title": "Conscious introspection leads to more self-deception?",
  "subtitle": null,
  "byline": "Tyler Cowen",
  "publishedAt": "2026-05-20T17:40:38.000Z",
  "contentHtml": "<blockquote><p>It seems, then, that we need another signal that can add precision to our introspection. And that signal is as follows: we are more likely to be lying to ourselves when we are engaging in&nbsp;<em>internal monologue</em>.</p>\n<p>An internal monologue is the experience of having concrete, “narration-style” thoughts as opposed to passive experiences. This argument maybe doesn’t apply to people with a constant internal monologue, or those who have none. But it seems like most people’s internal lives are some combination of subconscious thought and active monologue: most of our day-to-day moments are spent instinctively receiving and reacting to external stimuli, but in certain moments — e.g. when faced with difficult choices that require serious deliberation — our thoughts morph into something that resembles language as we try to articulate our feelings and ask ourselves questions.</p>\n<p>This is more likely to happen when there’s a divergence between your actual feelings and what you want your feelings to be.</p></blockquote>\n<p>Here is <a href=\"https://elizabethxli.substack.com/p/how-do-we-know-if-were-lying-to-ourselves\" target=\"_blank\" rel=\"noopener noreferrer\">more from Elizabeth Li</a>, via Tejas.</p>",
  "wordCount": 166,
  "imageCount": 0,
  "linkCount": 1
}
